home_console_sdk/__init__.py
home_console_sdk/_version.py
home_console_sdk/auth.py
home_console_sdk/client.py
home_console_sdk/config.py
home_console_sdk/db.py
home_console_sdk/events.py
home_console_sdk/exceptions.py
home_console_sdk/models.py
home_console_sdk/plugin.py
home_console_sdk/tasks.py
home_console_sdk-0.0.2.dist-info/METADATA
home_console_sdk-0.0.2.dist-info/WHEEL
home_console_sdk-0.0.2.dist-info/top_level.txt
home_console_sdk-0.0.2.dist-info/RECORD
